[{"id":"62","name":"La Defense / Chateau de Vincennes","code":"1","stations":[{"id":"2035-2154","name":"Chateau de Vincennes"},{"id":"2067-2116","name":"Berault"},{"id":"1725-2470","name":"Saint-Mande"},{"id":"1751-2429","name":"Porte de Vincennes"},{"id":"1832-2371","name":"Nation"},{"id":"1698-2443","name":"Reuilly-Diderot"},{"id":"1955-2210","name":"Gare de Lyon"},{"id":"2062-2111","name":"Bastille"},{"id":"1642-2522","name":"Saint-Paul (Le Marais)"},{"id":"1892-2288","name":"Hotel de Ville"},{"id":"2036-2155","name":"Chatelet"},{"id":"1864-2331","name":"Louvre-Rivoli"},{"id":"1773-2383","name":"Palais-Royal (Musee du Louvre)"},{"id":"1688-2498","name":"Tuileries"},{"id":"1980-2170","name":"Concorde"},{"id":"2083-2544","name":"Champs-Elysees-Clemenceau"},{"id":"1945-2200","name":"Franklin-Roosevelt"},{"id":"1961-2216","name":"George V"},{"id":"2028-2147","name":"Charles de Gaulle-Etoile"},{"id":"2048-2098","name":"Argentine"},{"id":"1755-2433","name":"Porte Maillot"},{"id":"1856-2323","name":"Les Sablons (Jardin d'acclimatation)"},{"id":"1803-2342","name":"Pont de Neuilly"},{"id":"1933-2258","name":"Esplanade de la Defense"},{"id":"1887-2283","name":"La Defense (Grande Arche)"}]},{"id":"67","name":"Porte Dauphine / Nation","code":"2","stations":[{"id":"1833-2338","name":"Nation"},{"id":"2058-2107","name":"Avron"},{"id":"2041-2160","name":"Alexandre-Dumas"},{"id":"1788-2398","name":"Philippe Auguste"},{"id":"1784-2394","name":"Pere-Lachaise"},{"id":"1812-2351","name":"Menilmontant"},{"id":"2079-2128","name":"Couronnes"},{"id":"2087-2548","name":"Belleville"},{"id":"1978-2168","name":"Colonel Fabien"},{"id":"1900-2296","name":"Jaures"},{"id":"1674-2484","name":"Stalingrad"},{"id":"1910-2235","name":"La Chapelle"},{"id":"2086-2547","name":"Barbes-Rochechouart"},{"id":"2046-2096","name":"Anvers"},{"id":"1791-2401","name":"Pigalle"},{"id":"2071-2120","name":"Blanche"},{"id":"1795-2405","name":"Place de Clichy"},{"id":"1707-2452","name":"Rome"},{"id":"1629-2509","name":"Villiers"},{"id":"1822-2361","name":"Monceau"},{"id":"1989-2179","name":"Courcelles"},{"id":"1684-2494","name":"Ternes"},{"id":"2029-2148","name":"Charles de Gaulle-Etoile"},{"id":"1694-2504","name":"Victor Hugo"},{"id":"1736-2414","name":"Porte Dauphine (Marechal de Lattre de Tassigny)"}]},{"id":"68","name":"Pont de Levallois - Becon / Gallieni","code":"3","stations":[{"id":"1949-2204","name":"Gallieni (Parc de Bagnolet)"},{"id":"1737-2415","name":"Porte de Bagnolet"},{"id":"1950-2205","name":"Gambetta"},{"id":"1785-2395","name":"Pere-Lachaise"},{"id":"1728-2471","name":"Rue Saint-Maur"},{"id":"1779-2389","name":"Parmentier"},{"id":"1766-2376","name":"Republique"},{"id":"1683-2493","name":"Temple"},{"id":"2050-2099","name":"Arts-et-Metiers"},{"id":"1765-2375","name":"Reaumur-Sebastopol"},{"id":"1662-2542","name":"Sentier"},{"id":"2007-2196","name":"Bourse"},{"id":"1760-2438","name":"Quatre Septembre"},{"id":"1846-2313","name":"Opera"},{"id":"1889-2285","name":"Havre-Caumartin"},{"id":"1722-2467","name":"Saint-Lazare"},{"id":"1935-2260","name":"Europe"},{"id":"1630-2510","name":"Villiers"},{"id":"1881-2277","name":"Malesherbes"},{"id":"1634-2514","name":"Wagram"},{"id":"1786-2396","name":"Pereire"},{"id":"1738-2416","name":"Porte de Champerret"},{"id":"1862-2329","name":"Louise Michel"},{"id":"2044-2163","name":"Anatole-France"},{"id":"1802-2341","name":"Pont de Levallois-Becon"}]},{"id":"69","name":"Gambetta / Porte des Lilas","code":"3b","stations":[{"id":"1752-2430","name":"Porte des Lilas"},{"id":"1718-2463","name":"Saint-Fargeau"},{"id":"1783-2393","name":"Pelleport"},{"id":"1659-2539","name":"Gambetta"}]},{"id":"70","name":"Mairie de Montrouge / Porte de Clignancourt","code":"4","stations":[{"id":"1742-2420","name":"Porte de Clignancourt"},{"id":"1668-2478","name":"Simplon"},{"id":"1655-2535","name":"Marcadet-Poissonniers"},{"id":"2033-2152","name":"Chateau Rouge"},{"id":"2061-2110","name":"Barbes-Rochechouart"},{"id":"1957-2212","name":"Gare du Nord"},{"id":"1953-2208","name":"Gare de l'Est (Verdun)"},{"id":"2034-2153","name":"Chateau d'Eau"},{"id":"1677-2487","name":"Strasbourg-Saint-Denis"},{"id":"1764-2374","name":"Reaumur-Sebastopol"},{"id":"1934-2259","name":"Etienne Marcel"},{"id":"1855-2322","name":"Les Halles"},{"id":"1964-2219","name":"Chatelet"},{"id":"1975-2230","name":"Cite"},{"id":"1729-2472","name":"Saint-Michel"},{"id":"1845-2312","name":"Odeon"},{"id":"1721-2466","name":"Saint-Germain des Pres"},{"id":"1733-2411","name":"Saint-Sulpice"},{"id":"1731-2442","name":"Saint-Placide"},{"id":"1824-2363","name":"Montparnasse-Bienvenue"},{"id":"1692-2502","name":"Vavin"},{"id":"1645-2525","name":"Raspail"},{"id":"1996-2185","name":"Denfert-Rochereau"},{"id":"1828-2367","name":"Mouton-Duvernet"},{"id":"2040-2159","name":"Alesia"},{"id":"1735-2413","name":"Porte d'Orleans (General Leclerc)"},{"id":"4028973-4028974","name":"Mairie de Montrouge"}]},{"id":"71","name":"Place d'Italie / Bobigny - Pablo Picasso","code":"5","stations":[{"id":"2089-2550","name":"Bobigny-Pablo-Picasso"},{"id":"2072-2121","name":"Bobigny-Pantin (Raymond Queneau)"},{"id":"1932-2257","name":"Eglise de Pantin"},{"id":"1891-2287","name":"Hoche"},{"id":"1746-2424","name":"Porte de Pantin"},{"id":"1772-2382","name":"Ourcq"},{"id":"1922-2247","name":"Laumiere"},{"id":"1901-2297","name":"Jaures"},{"id":"1675-2485","name":"Stalingrad"},{"id":"1958-2213","name":"Gare du Nord"},{"id":"2076-2125","name":"Gare de l'Est (Verdun)"},{"id":"1898-2294","name":"Jacques-Bonsergent"},{"id":"1767-2377","name":"Republique"},{"id":"1843-2310","name":"Oberkampf"},{"id":"1700-2445","name":"Richard-Lenoir"},{"id":"2008-2164","name":"Breguet-Sabin"},{"id":"2063-2112","name":"Bastille"},{"id":"1759-2437","name":"Quai de la Rapee"},{"id":"1951-2206","name":"Gare d'Austerlitz"},{"id":"1641-2521","name":"Saint-Marcel"},{"id":"2017-2136","name":"Campo-Formio"},{"id":"1793-2403","name":"Place d'Italie"}]},{"id":"72","name":"Charles de Gaulle - Etoile / Nation","code":"6","stations":[{"id":"1834-2339","name":"Nation"},{"id":"1789-2399","name":"Picpus"},{"id":"2065-2114","name":"Bel-Air"},{"id":"2081-2094","name":"Daumesnil (Felix Eboue)"},{"id":"2082-2543","name":"Dugommier"},{"id":"2068-2117","name":"Bercy"},{"id":"1644-2524","name":"Quai de la Gare"},{"id":"1974-2229","name":"Chevaleret"},{"id":"1836-2303","name":"Nationale"},{"id":"1794-2404","name":"Place d'Italie"},{"id":"1987-2177","name":"Corvisart"},{"id":"1962-2217","name":"Glaciere"},{"id":"1640-2520","name":"Saint-Jacques"},{"id":"1997-2186","name":"Denfert-Rochereau"},{"id":"1763-2409","name":"Raspail"},{"id":"1930-2255","name":"Edgar-Quinet"},{"id":"1825-2364","name":"Montparnasse-Bienvenue"},{"id":"1781-2391","name":"Pasteur"},{"id":"1665-2475","name":"Sevres-Lecourbe"},{"id":"2016-2135","name":"Cambronne"},{"id":"1657-2537","name":"La Motte-Picquet-Grenelle"},{"id":"1926-2251","name":"Dupleix"},{"id":"2069-2118","name":"Bir-Hakeim (Grenelle)"},{"id":"1780-2390","name":"Passy"},{"id":"1687-2497","name":"Trocadero"},{"id":"2073-2122","name":"Boissiere"},{"id":"1909-2234","name":"Kleber"},{"id":"2030-2149","name":"Charles de Gaulle-Etoile"}]},{"id":"73","name":"Villejuif-L. Aragon / Mairie d'Ivry / la Courneuve - 8 Mai 1945","code":"7","stations":[{"id":"1911-2236","name":"La Courneuve-8-Mai-1945"},{"id":"1944-2199","name":"Fort d'Aubervilliers"},{"id":"2055-2104","name":"Aubervilliers Pantin (4 Chemins)"},{"id":"1744-2422","name":"Porte de la Villette"},{"id":"1985-2175","name":"Corentin-Cariou"},{"id":"2080-2093","name":"Crimee"},{"id":"1703-2448","name":"Riquet"},{"id":"1676-2486","name":"Stalingrad"},{"id":"1860-2327","name":"Louis Blanc"},{"id":"2085-2546","name":"Chateau Landon"},{"id":"1954-2209","name":"Gare de l'Est (Verdun)"},{"id":"1800-2373","name":"Poissonniere"},{"id":"2015-2134","name":"Cadet"},{"id":"1849-2316","name":"Le Peletier"},{"id":"1971-2226","name":"Chaussee d'Antin (La Fayette)"},{"id":"1847-2314","name":"Opera"},{"id":"1757-2435","name":"Pyramides"},{"id":"1774-2384","name":"Palais-Royal (Musee du Louvre)"},{"id":"1806-2345","name":"Pont Neuf"},{"id":"1966-2221","name":"Chatelet"},{"id":"1805-2344","name":"Pont Marie (Cite des Arts)"},{"id":"1681-2491","name":"Sully-Morland"},{"id":"1907-2232","name":"Jussieu"},{"id":"1649-2529","name":"Place Monge (Jardin des Plantes)"},{"id":"2020-2139","name":"Censier-Daubenton"},{"id":"1854-2321","name":"Les Gobelins"},{"id":"1648-2528","name":"Place d'Italie"},{"id":"1685-2495","name":"Tolbiac"},{"id":"1876-2272","name":"Maison Blanche"},{"id":"1808-2347","name":"Porte d'Italie"},{"id":"1740-2418","name":"Porte de Choisy"},{"id":"1734-2412","name":"Porte d'Ivry"},{"id":"1790-2400","name":"Pierre et Marie Curie"},{"id":"1871-2301","name":"Mairie d'Ivry"},{"id":"1925-2250","name":"Le Kremlin-Bicetre"},{"id":"1639-2519","name":"Villejuif-Leo Lagrange"},{"id":"1696-2506","name":"Villejuif-Paul Vaillant Couturier (Hopital Paul Brousse)"},{"id":"1695-2505","name":"Villejuif-Louis Aragon"}]},{"id":"74","name":"Louis Blanc / Pre-Saint-Gervais","code":"7b","stations":[{"id":"1756-2434","name":"Pre-Saint-Gervais"},{"id":"1635-","name":"Danube"},{"id":"2002-2191","name":"Botzaris"},{"id":"2013-2132","name":"Buttes-Chaumont"},{"id":"2075-2124","name":"Bolivar"},{"id":"1902-2298","name":"Jaures"},{"id":"1861-2328","name":"Louis Blanc"},{"id":"-1797","name":"Place des Fetes"}]},{"id":"172562","name":"Pointe du Lac / Balar","code":"8","stations":[{"id":"3343334-3343335","name":"Balard"},{"id":"3343336-3343337","name":"Lourmel"},{"id":"3343338-3343339","name":"Boucicaut"},{"id":"3343746-3343752","name":"Felix Faure"},{"id":"3343753-3343754","name":"Commerce"},{"id":"3343755-3343756","name":"La Motte-Picquet-Grenelle"},{"id":"3343757-3343758","name":"Ecole Militaire"},{"id":"3343759-3343760","name":"La Tour-Maubourg"},{"id":"3343761-3343762","name":"Invalides"},{"id":"3343763-3343764","name":"Concorde"},{"id":"3343765-3343766","name":"Madeleine"},{"id":"3343767-3343768","name":"Opera"},{"id":"3343769-3343770","name":"Richelieu-Drouot"},{"id":"3343771-3343772","name":"Grands Boulevards"},{"id":"3343773-3343774","name":"Bonne Nouvelle"},{"id":"3343775-3343776","name":"Strasbourg-Saint-Denis"},{"id":"3343777-3343778","name":"Republique"},{"id":"3343779-3343780","name":"Filles du Calvaire"},{"id":"3343781-3343782","name":"Saint-Sebastien-Froissart"},{"id":"3343783-3343784","name":"Chemin Vert"},{"id":"3343785-3343786","name":"Bastille"},{"id":"3343787-3343788","name":"Ledru-Rollin"},{"id":"3343789-3343790","name":"Faidherbe-Chaligny"},{"id":"3343791-3343792","name":"Reuilly-Diderot"},{"id":"3343793-3343794","name":"Montgallet"},{"id":"3343795-3343796","name":"Daumesnil (Felix Eboue)"},{"id":"3343797-3343798","name":"Michel Bizot"},{"id":"3343799-3343800","name":"Porte Doree"},{"id":"3343801-3343802","name":"Porte de Charenton"},{"id":"3343803-3343804","name":"Liberte"},{"id":"3343805-3343806","name":"Charenton-Ecoles"},{"id":"3343807-3343808","name":"Ecole Veterinaire de Maisons-Alfort"},{"id":"3343809-3343810","name":"Maisons-Alfort-Stade"},{"id":"3343811-3343812","name":"Maisons-Alfort-Les Juilliottes"},{"id":"3343813-3343814","name":"Creteil-L'Echat (Hopital Henri Mondor)"},{"id":"3343815-3343816","name":"Creteil-Universite"},{"id":"3343817-3343818","name":"Creteil-Prefecture (Hotel de Ville)"},{"id":"3343819-3343825","name":"Pointe du Lac"}]},{"id":"76","name":"Mairie de Montreuil / Pont de Sevres","code":"9","stations":[{"id":"1804-2343","name":"Pont de Sevres"},{"id":"2088-2549","name":"Billancourt"},{"id":"1884-2280","name":"Marcel Sembat"},{"id":"1747-2425","name":"Porte de Saint-Cloud"},{"id":"1936-2261","name":"Exelmans"},{"id":"1816-2355","name":"Michel-Ange-Molitor"},{"id":"1814-2353","name":"Michel-Ange-Auteuil"},{"id":"1899-2295","name":"Jasmin"},{"id":"1762-2440","name":"Ranelagh"},{"id":"1917-2242","name":"La Muette"},{"id":"1708-2453","name":"Rue de la Pompe (Avenue Georges Mandel)"},{"id":"1637-2517","name":"Trocadero"},{"id":"1895-2291","name":"Iena"},{"id":"2043-2162","name":"Alma-Marceau"},{"id":"1946-2201","name":"Franklin-Roosevelt"},{"id":"1730-2441","name":"Saint-Philippe du Roule"},{"id":"1819-2358","name":"Miromesnil"},{"id":"1715-2460","name":"Saint-Augustin"},{"id":"1890-2286","name":"Havre-Caumartin"},{"id":"1972-2227","name":"Chaussee d'Antin (La Fayette)"},{"id":"1702-2447","name":"Richelieu-Drouot"},{"id":"1712-2457","name":"Grands Boulevards"},{"id":"2001-2190","name":"Bonne Nouvelle"},{"id":"1678-2488","name":"Strasbourg-Saint-Denis"},{"id":"1647-2527","name":"Republique"},{"id":"1844-2311","name":"Oberkampf"},{"id":"1714-2459","name":"Saint-Ambroise"},{"id":"1633-2513","name":"Voltaire (Leon Blum)"},{"id":"2032-2151","name":"Charonne"},{"id":"1709-2454","name":"Rue des Boulets"},{"id":"1651-2531","name":"Nation"},{"id":"2014-2133","name":"Buzenval"},{"id":"1882-2278","name":"Maraichers"},{"id":"1745-2423","name":"Porte de Montreuil"},{"id":"1704-2449","name":"Robespierre"},{"id":"1993-2183","name":"Croix-de-Chavaux (Jacques Duclos)"},{"id":"1873-2269","name":"Mairie de Montreuil"}]},{"id":"63","name":"Gare d'Austerlitz / Boulogne - Pont de Saint Cloud","code":"10","stations":[{"id":"2005-2194","name":"Boulogne Pont de Saint-Cloud"},{"id":"2004-2193","name":"Boulogne-Jean-Jaures"},{"id":"8433-2346","name":"Porte d'Auteuil"},{"id":"1817-","name":"Michel-Ange-Molitor"},{"id":"2026-","name":"Chardon-Lagache"},{"id":"1818-","name":"Mirabeau"},{"id":"1903-2299","name":"Javel-Andre-Citroen"},{"id":"2031-2150","name":"Charles Michels"},{"id":"2057-2106","name":"Avenue Emile-Zola"},{"id":"1916-2241","name":"La Motte-Picquet-Grenelle"},{"id":"1661-2541","name":"Segur"},{"id":"1927-2252","name":"Duroc"},{"id":"1690-2500","name":"Vaneau"},{"id":"1666-2476","name":"Sevres-Babylone"},{"id":"1867-2334","name":"Mabillon"},{"id":"1653-2533","name":"Odeon"},{"id":"1977-2167","name":"Cluny-La Sorbonne"},{"id":"1811-2350","name":"Maubert-Mutualite"},{"id":"2018-2137","name":"Cardinal-Lemoine"},{"id":"1908-2233","name":"Jussieu"},{"id":"1952-2207","name":"Gare d'Austerlitz"},{"id":"-2256","name":"Eglise d'Auteuil"},{"id":"-2354","name":"Michel-Ange-Auteuil"}]},{"id":"64","name":"Chatelet / Mairie des Lilas","code":"11","stations":[{"id":"1875-2271","name":"Mairie des Lilas"},{"id":"1753-2431","name":"Porte des Lilas"},{"id":"1682-2492","name":"Telegraphe"},{"id":"1798-2408","name":"Place des Fetes"},{"id":"1905-2266","name":"Jourdain"},{"id":"1758-2436","name":"Pyrenees"},{"id":"2066-2115","name":"Belleville"},{"id":"1963-2218","name":"Goncourt (Hopital Saint-Louis)"},{"id":"967988-967989","name":"Republique"},{"id":"2051-2100","name":"Arts-et-Metiers"},{"id":"1761-2439","name":"Rambuteau"},{"id":"1893-2289","name":"Hotel de Ville"},{"id":"1965-2220","name":"Chatelet"}]},{"id":"65","name":"Front Populaire / Mairie d'Issy","code":"12","stations":[{"id":"1870-2337","name":"Mairie d'Issy"},{"id":"1986-2176","name":"Corentin-Celton"},{"id":"1750-2428","name":"Porte de Versailles"},{"id":"1984-2174","name":"Convention"},{"id":"1691-2501","name":"Vaugirard (Adolphe Cherioux)"},{"id":"1632-2512","name":"Volontaires"},{"id":"1782-2392","name":"Pasteur"},{"id":"1938-2263","name":"Falguiere"},{"id":"1826-2365","name":"Montparnasse-Bienvenue"},{"id":"1842-2309","name":"Notre-Dame des Champs"},{"id":"1646-2526","name":"Rennes"},{"id":"1667-2477","name":"Sevres-Babylone"},{"id":"1710-2455","name":"Rue du Bac"},{"id":"1669-2479","name":"Solferino"},{"id":"2052-2101","name":"Assemblee Nationale"},{"id":"1982-2172","name":"Concorde"},{"id":"1869-2336","name":"Madeleine"},{"id":"1723-2468","name":"Saint-Lazare"},{"id":"1686-2496","name":"Trinite-d'Estienne d'Orves"},{"id":"1841-2308","name":"Notre-Dame de Lorette"},{"id":"1720-2465","name":"Saint-Georges"},{"id":"1792-2402","name":"Pigalle"},{"id":"2037-2156","name":"Abbesses"},{"id":"1920-2245","name":"Lamarck-Caulaincourt"},{"id":"1906-2267","name":"Jules Joffrin"},{"id":"1883-2279","name":"Marcadet-Poissonniers"},{"id":"1886-2282","name":"Marx-Dormoy"},{"id":"1743-2421","name":"Porte de la Chapelle"},{"id":"3901291-3901292","name":"Front Populaire"}]},{"id":"66","name":"St-Denis-Universite/Les Courtilles / Chatillon - Montrouge","code":"13","stations":[{"id":"1969-2224","name":"Chatillon Montrouge"},{"id":"1880-2276","name":"Malakoff-Rue Etienne Dolet"},{"id":"1879-2275","name":"Malakoff-Plateau de Vanves"},{"id":"1749-2427","name":"Porte de Vanves"},{"id":"1799-2372","name":"Plaisance"},{"id":"1787-2397","name":"Pernety"},{"id":"1948-2203","name":"Gaite"},{"id":"1827-2366","name":"Montparnasse-Bienvenue"},{"id":"1928-2253","name":"Duroc"},{"id":"1719-2464","name":"Saint-Francois-Xavier"},{"id":"1638-2518","name":"Varenne"},{"id":"1897-2293","name":"Invalides"},{"id":"2025-2144","name":"Champs-Elysees-Clemenceau"},{"id":"1820-2359","name":"Miromesnil"},{"id":"1724-2469","name":"Saint-Lazare"},{"id":"1858-2325","name":"Liege"},{"id":"1796-2406","name":"Place de Clichy"},{"id":"1656-2536","name":"La Fourche"},{"id":"1888-2284","name":"Guy-Moquet"},{"id":"1748-2426","name":"Porte de Saint-Ouen"},{"id":"1959-2214","name":"Garibaldi"},{"id":"1874-2270","name":"Mairie de Saint-Ouen"},{"id":"1692060-1692061","name":"Carrefour-Pleyel"},{"id":"1717-2462","name":"Saint-Denis - Porte de Paris"},{"id":"1716-2461","name":"Basilique de Saint-Denis"},{"id":"140078-140079","name":"Saint-Denis-Universite"},{"id":"2009-2165","name":"Brochant"},{"id":"1741-2419","name":"Porte de Clichy"},{"id":"1872-2268","name":"Mairie de Clichy"},{"id":"1947-2202","name":"Gabriel-Peri"},{"id":"1662795-1662796","name":"Les Agnettes"},{"id":"1662797-1662798","name":"Asnieres-Gennevilliers Les Courtilles"}]},{"id":"55098","name":"Olympiades / Saint-Lazare","code":"14","stations":[{"id":"1166840-1166841","name":"Saint-Lazare"},{"id":"1166838-1166839","name":"Madeleine"},{"id":"6129304-6129305","name":"Pyramides"},{"id":"1166834-1166835","name":"Chatelet"},{"id":"1166832-1166833","name":"Gare de Lyon"},{"id":"1166830-1166831","name":"Bercy"},{"id":"1166828-1166829","name":"Cour Saint-Emilion"},{"id":"1166826-1166827","name":"Bibliotheque-Francois Mitterrand"},{"id":"1166824-1166825","name":"Olympiades"}]},{"id":"79","name":"Funiculaire","code":"Fun","stations":[{"id":"2090-2551","name":"Funiculaire Gare basse"},{"id":"2091-2552","name":"Funiculaire Gare haute"}]},{"id":"455","name":"Orly 4 / Antony-RER","code":"Orv","stations":[{"id":"22789-22790","name":"Antony"},{"id":"22791-22792","name":"Orly 1-2-3"},{"id":"22793-22794","name":"Orly 4"}]}]